nora_lib/__init__.py
nora_lib/py.typed
nora_lib/serializers.py
nora_lib/impl/__init__.py
nora_lib/impl/pubsub.py
nora_lib/impl/context/__init__.py
nora_lib/impl/context/agent_context.py
nora_lib/impl/context/context_service.py
nora_lib/impl/context/models.py
nora_lib/impl/interactions/__init__.py
nora_lib/impl/interactions/interactions_service.py
nora_lib/impl/interactions/models.py
nora_lib/impl/interactions/step_progress.py
nora_lib/impl/tasks/__init__.py
nora_lib/impl/tasks/state.py
nora_lib/progress/__init__.py
nora_lib/progress/models.py
nora_lib/progress/reporter.py
nora_lib/tasks/__init__.py
nora_lib/tasks/models.py
nora_lib/tasks/state.py
nora_lib_impl-1.8.2.dist-info/METADATA
nora_lib_impl-1.8.2.dist-info/WHEEL
nora_lib_impl-1.8.2.dist-info/top_level.txt
nora_lib_impl-1.8.2.dist-info/RECORD
