Metadata-Version: 2.4
Name: nora_lib-impl
Version: 1.8.2
Summary: For making and coordinating agents and tools
Home-page: https://github.com/allenai/nora_lib/impl
Requires-Python: >=3.9
Requires-Dist: pydantic<3,>=2
Requires-Dist: requests
Requires-Dist: boto3
Requires-Dist: aws_requests_auth
Requires-Dist: retry
Provides-Extra: dev
Requires-Dist: mypy; extra == "dev"
Requires-Dist: pytest; extra == "dev"
Requires-Dist: black; extra == "dev"
Requires-Dist: types-requests; extra == "dev"
Dynamic: home-page
Dynamic: provides-extra
Dynamic: requires-dist
Dynamic: requires-python
Dynamic: summary
